peasy_logs/__init__.py
peasy_logs/main.py
peasy_logs/tests/test_capturing.py
peasy_logs-0.1.0.dist-info/WHEEL
peasy_logs-0.1.0.dist-info/METADATA
peasy_logs-0.1.0.dist-info/RECORD
