Metadata-Version: 2.1
Name: peasy-logs
Version: 0.1.0
Summary: Easily ship you logs from functions to various connectors!
License: MIT
Author: larsheinen
Author-email: larsheinen@gmail.com
Requires-Python: >=3.7,<4.0
Classifier: License :: OSI Approved :: MIT License
Classifier: Programming Language :: Python :: 3
Classifier: Programming Language :: Python :: 3.10
Classifier: Programming Language :: Python :: 3.7
Classifier: Programming Language :: Python :: 3.8
Classifier: Programming Language :: Python :: 3.9
Requires-Dist: requests (>=2.27.1,<3.0.0)
